easy_html/__init__.py
easy_html/_version.py
easy_html/font.py
easy_html/generator.py
easy_html/pdf.py
easy_html/templates.py
easy_html/types.py
py_easy_html-0.0.2.dist-info/LICENSE
py_easy_html-0.0.2.dist-info/METADATA
py_easy_html-0.0.2.dist-info/WHEEL
py_easy_html-0.0.2.dist-info/top_level.txt
py_easy_html-0.0.2.dist-info/RECORD
